{"@context":"http://iiif.io/api/presentation/2/context.json","@id":"https://cdm16281.contentdm.oclc.org/iiif/info/p16281coll17/manifest.json","@type":"sc:Collection","label":"U.S. Forest Service","manifests":[{"@type":"sc:Manifest","@id":"https://cdm16281.contentdm.oclc.org/iiif/info/p16281coll17/0/manifest.json","label":"Payette River"},{"@type":"sc:Manifest","@id":"https://cdm16281.contentdm.oclc.org/iiif/info/p16281coll17/1/manifest.json","label":"Tamarack Tie Timber"},{"@type":"sc:Manifest","@id":"https://cdm16281.contentdm.oclc.org/iiif/info/p16281coll17/2/manifest.json","label":"Pile of Ties"},{"@type":"sc:Manifest","@id":"https://cdm16281.contentdm.oclc.org/iiif/info/p16281coll17/3/manifest.json","label":"Railroad Ties Loaded on A Wagon"},{"@type":"sc:Manifest","@id":"https://cdm16281.contentdm.oclc.org/iiif/info/p16281coll17/4/manifest.json","label":"Stack of Railroad Ties"},{"@type":"sc:Manifest","@id":"https://cdm16281.contentdm.oclc.org/iiif/info/p16281coll17/5/manifest.json","label":"Scott Mountain"},{"@type":"sc:Manifest","@id":"https://cdm16281.contentdm.oclc.org/iiif/info/p16281coll17/6/manifest.json","label":"Scriver Flats"},{"@type":"sc:Manifest","@id":"https://cdm16281.contentdm.oclc.org/iiif/info/p16281coll17/7/manifest.json","label":"Northwest of Banks Depot (a)"},{"@type":"sc:Manifest","@id":"https://cdm16281.contentdm.oclc.org/iiif/info/p16281coll17/8/manifest.json","label":"Northwest of Banks Depot (b)"},{"@type":"sc:Manifest","@id":"https://cdm16281.contentdm.oclc.org/iiif/info/p16281coll17/9/manifest.json","label":"Northwest of Banks Depot (c)"},{"@type":"sc:Manifest","@id":"https://cdm16281.contentdm.oclc.org/iiif/info/p16281coll17/10/manifest.json","label":"Construction of Hay Shed"},{"@type":"sc:Manifest","@id":"https://cdm16281.contentdm.oclc.org/iiif/info/p16281coll17/11/manifest.json","label":"Nelson Creek"},{"@type":"sc:Manifest","@id":"https://cdm16281.contentdm.oclc.org/iiif/info/p16281coll17/13/manifest.json","label":"Forest Guard on Scriver Creek Trail"},{"@type":"sc:Manifest","@id":"https://cdm16281.contentdm.oclc.org/iiif/info/p16281coll17/14/manifest.json","label":"Logs at Nelson Creek"},{"@type":"sc:Manifest","@id":"https://cdm16281.contentdm.oclc.org/iiif/info/p16281coll17/15/manifest.json","label":"Big Creek"},{"@type":"sc:Manifest","@id":"https://cdm16281.contentdm.oclc.org/iiif/info/p16281coll17/16/manifest.json","label":"Logs in Shallow Water"},{"@type":"sc:Manifest","@id":"https://cdm16281.contentdm.oclc.org/iiif/info/p16281coll17/17/manifest.json","label":"South Fork Payette River (c)"},{"@type":"sc:Manifest","@id":"https://cdm16281.contentdm.oclc.org/iiif/info/p16281coll17/18/manifest.json","label":"Cutting at Lower Scriver Creek"},{"@type":"sc:Manifest","@id":"https://cdm16281.contentdm.oclc.org/iiif/info/p16281coll17/19/manifest.json","label":"Raspberry Thicket"},{"@type":"sc:Manifest","@id":"https://cdm16281.contentdm.oclc.org/iiif/info/p16281coll17/20/manifest.json","label":"Wagon Wheel Jammed"},{"@type":"sc:Manifest","@id":"https://cdm16281.contentdm.oclc.org/iiif/info/p16281coll17/21/manifest.json","label":"Weighing Ewes"},{"@type":"sc:Manifest","@id":"https://cdm16281.contentdm.oclc.org/iiif/info/p16281coll17/22/manifest.json","label":"Weighing Ewes"},{"@type":"sc:Manifest","@id":"https://cdm16281.contentdm.oclc.org/iiif/info/p16281coll17/23/manifest.json","label":"Tripod Meadows"},{"@type":"sc:Manifest","@id":"https://cdm16281.contentdm.oclc.org/iiif/info/p16281coll17/24/manifest.json","label":"Old Burn"},{"@type":"sc:Manifest","@id":"https://cdm16281.contentdm.oclc.org/iiif/info/p16281coll17/25/manifest.json","label":"Piling Brush"},{"@type":"sc:Manifest","@id":"https://cdm16281.contentdm.oclc.org/iiif/info/p16281coll17/26/manifest.json","label":"Cutting Ties"},{"@type":"sc:Manifest","@id":"https://cdm16281.contentdm.oclc.org/iiif/info/p16281coll17/27/manifest.json","label":"Lookout Trail"},{"@type":"sc:Manifest","@id":"https://cdm16281.contentdm.oclc.org/iiif/info/p16281coll17/28/manifest.json","label":"Garden Valley"},{"@type":"sc:Manifest","@id":"https://cdm16281.contentdm.oclc.org/iiif/info/p16281coll17/29/manifest.json","label":"Pack String on Rock Trail"},{"@type":"sc:Manifest","@id":"https://cdm16281.contentdm.oclc.org/iiif/info/p16281coll17/30/manifest.json","label":"Ruined Arastra"},{"@type":"sc:Manifest","@id":"https://cdm16281.contentdm.oclc.org/iiif/info/p16281coll17/31/manifest.json","label":"Sheep"},{"@type":"sc:Manifest","@id":"https://cdm16281.contentdm.oclc.org/iiif/info/p16281coll17/32/manifest.json","label":"Pack Horse Roany"},{"@type":"sc:Manifest","@id":"https://cdm16281.contentdm.oclc.org/iiif/info/p16281coll17/33/manifest.json","label":"Pack Horses Roddy"},{"@type":"sc:Manifest","@id":"https://cdm16281.contentdm.oclc.org/iiif/info/p16281coll17/34/manifest.json","label":"Pack Horse"},{"@type":"sc:Manifest","@id":"https://cdm16281.contentdm.oclc.org/iiif/info/p16281coll17/35/manifest.json","label":"Chute"},{"@type":"sc:Manifest","@id":"https://cdm16281.contentdm.oclc.org/iiif/info/p16281coll17/36/manifest.json","label":"Loading Roads"},{"@type":"sc:Manifest","@id":"https://cdm16281.contentdm.oclc.org/iiif/info/p16281coll17/37/manifest.json","label":"Camping Sign"},{"@type":"sc:Manifest","@id":"https://cdm16281.contentdm.oclc.org/iiif/info/p16281coll17/39/manifest.json","label":"Ground Sluicing"},{"@type":"sc:Manifest","@id":"https://cdm16281.contentdm.oclc.org/iiif/info/p16281coll17/40/manifest.json","label":"Wilson Warm Creek"},{"@type":"sc:Manifest","@id":"https://cdm16281.contentdm.oclc.org/iiif/info/p16281coll17/41/manifest.json","label":"Zimmerman Homestead"},{"@type":"sc:Manifest","@id":"https://cdm16281.contentdm.oclc.org/iiif/info/p16281coll17/42/manifest.json","label":"Rattlesnake Flat"},{"@type":"sc:Manifest","@id":"https://cdm16281.contentdm.oclc.org/iiif/info/p16281coll17/43/manifest.json","label":"Tripod Lookout"},{"@type":"sc:Manifest","@id":"https://cdm16281.contentdm.oclc.org/iiif/info/p16281coll17/44/manifest.json","label":"Big Eddy"},{"@type":"sc:Manifest","@id":"https://cdm16281.contentdm.oclc.org/iiif/info/p16281coll17/45/manifest.json","label":"Reconnaissance Camp"},{"@type":"sc:Manifest","@id":"https://cdm16281.contentdm.oclc.org/iiif/info/p16281coll17/46/manifest.json","label":"Dry Buck Hill"},{"@type":"sc:Manifest","@id":"https://cdm16281.contentdm.oclc.org/iiif/info/p16281coll17/47/manifest.json","label":"Idaho Northern Railroad Construction"},{"@type":"sc:Manifest","@id":"https://cdm16281.contentdm.oclc.org/iiif/info/p16281coll17/48/manifest.json","label":"North Fork of Payette"},{"@type":"sc:Manifest","@id":"https://cdm16281.contentdm.oclc.org/iiif/info/p16281coll17/49/manifest.json","label":"Station Men"},{"@type":"sc:Manifest","@id":"https://cdm16281.contentdm.oclc.org/iiif/info/p16281coll17/50/manifest.json","label":"Rock Debris"},{"@type":"sc:Manifest","@id":"https://cdm16281.contentdm.oclc.org/iiif/info/p16281coll17/51/manifest.json","label":"Construction Camp"},{"@type":"sc:Manifest","@id":"https://cdm16281.contentdm.oclc.org/iiif/info/p16281coll17/52/manifest.json","label":"North Fork Wagon Road (a)"},{"@type":"sc:Manifest","@id":"https://cdm16281.contentdm.oclc.org/iiif/info/p16281coll17/53/manifest.json","label":"North Fork Wagon Road (b)"},{"@type":"sc:Manifest","@id":"https://cdm16281.contentdm.oclc.org/iiif/info/p16281coll17/54/manifest.json","label":"Booms Above the Splash Dam"},{"@type":"sc:Manifest","@id":"https://cdm16281.contentdm.oclc.org/iiif/info/p16281coll17/55/manifest.json","label":"Yellow Pine"},{"@type":"sc:Manifest","@id":"https://cdm16281.contentdm.oclc.org/iiif/info/p16281coll17/56/manifest.json","label":"Tramway and Lumber Piles"},{"@type":"sc:Manifest","@id":"https://cdm16281.contentdm.oclc.org/iiif/info/p16281coll17/57/manifest.json","label":"Unloading Logs"},{"@type":"sc:Manifest","@id":"https://cdm16281.contentdm.oclc.org/iiif/info/p16281coll17/58/manifest.json","label":"Logging Team"},{"@type":"sc:Manifest","@id":"https://cdm16281.contentdm.oclc.org/iiif/info/p16281coll17/59/manifest.json","label":"Splash Dam"},{"@type":"sc:Manifest","@id":"https://cdm16281.contentdm.oclc.org/iiif/info/p16281coll17/60/manifest.json","label":"Deadwood Basin"},{"@type":"sc:Manifest","@id":"https://cdm16281.contentdm.oclc.org/iiif/info/p16281coll17/61/manifest.json","label":"Band of Sheep Grazing"},{"@type":"sc:Manifest","@id":"https://cdm16281.contentdm.oclc.org/iiif/info/p16281coll17/62/manifest.json","label":"Reconnaissance Party Moving Camp"},{"@type":"sc:Manifest","@id":"https://cdm16281.contentdm.oclc.org/iiif/info/p16281coll17/63/manifest.json","label":"Packing up Reconnaissance Party"},{"@type":"sc:Manifest","@id":"https://cdm16281.contentdm.oclc.org/iiif/info/p16281coll17/64/manifest.json","label":"Reconnaissance Party Lunch"},{"@type":"sc:Manifest","@id":"https://cdm16281.contentdm.oclc.org/iiif/info/p16281coll17/65/manifest.json","label":"Last Camp of Reconnaissance Party"},{"@type":"sc:Manifest","@id":"https://cdm16281.contentdm.oclc.org/iiif/info/p16281coll17/66/manifest.json","label":"Reconnaissance Party Moving"},{"@type":"sc:Manifest","@id":"https://cdm16281.contentdm.oclc.org/iiif/info/p16281coll17/67/manifest.json","label":"Reconnaissance Party Anderson Creek"},{"@type":"sc:Manifest","@id":"https://cdm16281.contentdm.oclc.org/iiif/info/p16281coll17/68/manifest.json","label":"Hell's Half Mile"},{"@type":"sc:Manifest","@id":"https://cdm16281.contentdm.oclc.org/iiif/info/p16281coll17/69/manifest.json","label":"Marking Board Personnel"},{"@type":"sc:Manifest","@id":"https://cdm16281.contentdm.oclc.org/iiif/info/p16281coll17/70/manifest.json","label":"South Fork Payette River (a)"},{"@type":"sc:Manifest","@id":"https://cdm16281.contentdm.oclc.org/iiif/info/p16281coll17/71/manifest.json","label":"Camp at Warm Springs"},{"@type":"sc:Manifest","@id":"https://cdm16281.contentdm.oclc.org/iiif/info/p16281coll17/72/manifest.json","label":"Crossing Five Mile Creek"},{"@type":"sc:Manifest","@id":"https://cdm16281.contentdm.oclc.org/iiif/info/p16281coll17/73/manifest.json","label":"Supervisor Grandjean Fording Creek"},{"@type":"sc:Manifest","@id":"https://cdm16281.contentdm.oclc.org/iiif/info/p16281coll17/74/manifest.json","label":"Garden Valley Ranger Station"},{"@type":"sc:Manifest","@id":"https://cdm16281.contentdm.oclc.org/iiif/info/p16281coll17/75/manifest.json","label":"Supervisor E. A. Grandjean"},{"@type":"sc:Manifest","@id":"https://cdm16281.contentdm.oclc.org/iiif/info/p16281coll17/76/manifest.json","label":"Dry Buck Sawmill"},{"@type":"sc:Manifest","@id":"https://cdm16281.contentdm.oclc.org/iiif/info/p16281coll17/79/manifest.json","label":"Seeding Crew"},{"@type":"sc:Manifest","@id":"https://cdm16281.contentdm.oclc.org/iiif/info/p16281coll17/80/manifest.json","label":"W. P. Dymoke's Residence"},{"@type":"sc:Manifest","@id":"https://cdm16281.contentdm.oclc.org/iiif/info/p16281coll17/81/manifest.json","label":"Boiling Springs"},{"@type":"sc:Manifest","@id":"https://cdm16281.contentdm.oclc.org/iiif/info/p16281coll17/82/manifest.json","label":"Hardscrabble Ranger Station"},{"@type":"sc:Manifest","@id":"https://cdm16281.contentdm.oclc.org/iiif/info/p16281coll17/83/manifest.json","label":"Dam on Payette River"},{"@type":"sc:Manifest","@id":"https://cdm16281.contentdm.oclc.org/iiif/info/p16281coll17/84/manifest.json","label":"Sawmill and Homestead"},{"@type":"sc:Manifest","@id":"https://cdm16281.contentdm.oclc.org/iiif/info/p16281coll17/85/manifest.json","label":"Oxbow Dam and Tunnel"},{"@type":"sc:Manifest","@id":"https://cdm16281.contentdm.oclc.org/iiif/info/p16281coll17/86/manifest.json","label":"Oxbow Dam and Tunnel"},{"@type":"sc:Manifest","@id":"https://cdm16281.contentdm.oclc.org/iiif/info/p16281coll17/87/manifest.json","label":"Golden Treasure Mining Company"},{"@type":"sc:Manifest","@id":"https://cdm16281.contentdm.oclc.org/iiif/info/p16281coll17/88/manifest.json","label":"Payette Ranger Station"},{"@type":"sc:Manifest","@id":"https://cdm16281.contentdm.oclc.org/iiif/info/p16281coll17/89/manifest.json","label":"J. C. Carter Homestead"},{"@type":"sc:Manifest","@id":"https://cdm16281.contentdm.oclc.org/iiif/info/p16281coll17/90/manifest.json","label":"W. J. Hopkins' Homestead"},{"@type":"sc:Manifest","@id":"https://cdm16281.contentdm.oclc.org/iiif/info/p16281coll17/91/manifest.json","label":"Joe Hessler's Cabin"},{"@type":"sc:Manifest","@id":"https://cdm16281.contentdm.oclc.org/iiif/info/p16281coll17/92/manifest.json","label":"Joe Hessler's Orchard"},{"@type":"sc:Manifest","@id":"https://cdm16281.contentdm.oclc.org/iiif/info/p16281coll17/93/manifest.json","label":"Dredge at Idaho City"},{"@type":"sc:Manifest","@id":"https://cdm16281.contentdm.oclc.org/iiif/info/p16281coll17/94/manifest.json","label":"Chain of Buckets"},{"@type":"sc:Manifest","@id":"https://cdm16281.contentdm.oclc.org/iiif/info/p16281coll17/95/manifest.json","label":"Machine Shop"},{"@type":"sc:Manifest","@id":"https://cdm16281.contentdm.oclc.org/iiif/info/p16281coll17/96/manifest.json","label":"Dredge"},{"@type":"sc:Manifest","@id":"https://cdm16281.contentdm.oclc.org/iiif/info/p16281coll17/97/manifest.json","label":"Warm Lake"},{"@type":"sc:Manifest","@id":"https://cdm16281.contentdm.oclc.org/iiif/info/p16281coll17/98/manifest.json","label":"Damaged Lodgepole"},{"@type":"sc:Manifest","@id":"https://cdm16281.contentdm.oclc.org/iiif/info/p16281coll17/100/manifest.json","label":"Hard Rock Work"},{"@type":"sc:Manifest","@id":"https://cdm16281.contentdm.oclc.org/iiif/info/p16281coll17/101/manifest.json","label":"Shows Growth of Grass"},{"@type":"sc:Manifest","@id":"https://cdm16281.contentdm.oclc.org/iiif/info/p16281coll17/102/manifest.json","label":"Bedground (a)"},{"@type":"sc:Manifest","@id":"https://cdm16281.contentdm.oclc.org/iiif/info/p16281coll17/103/manifest.json","label":"Lodgepole Seedling"},{"@type":"sc:Manifest","@id":"https://cdm16281.contentdm.oclc.org/iiif/info/p16281coll17/104/manifest.json","label":"Bedground (b)"},{"@type":"sc:Manifest","@id":"https://cdm16281.contentdm.oclc.org/iiif/info/p16281coll17/105/manifest.json","label":"Planting Camp (a)"},{"@type":"sc:Manifest","@id":"https://cdm16281.contentdm.oclc.org/iiif/info/p16281coll17/106/manifest.json","label":"Planting Camp (b)"},{"@type":"sc:Manifest","@id":"https://cdm16281.contentdm.oclc.org/iiif/info/p16281coll17/107/manifest.json","label":"South Fork Road"},{"@type":"sc:Manifest","@id":"https://cdm16281.contentdm.oclc.org/iiif/info/p16281coll17/135/manifest.json","label":"William Eagleson"}],"total":104}